sshot/__init__.py
sshot/background.py
sshot/config.py
sshot/debug.py
sshot/easy.py
sshot/imageproc.py
sshot/tokenproc.py
sourceshot-2.0.1.dist-info/METADATA
sourceshot-2.0.1.dist-info/WHEEL
sourceshot-2.0.1.dist-info/entry_points.txt
sourceshot-2.0.1.dist-info/top_level.txt
sourceshot-2.0.1.dist-info/RECORD
