Metadata-Version: 2.1
Name: sourceshot
Version: 2.0.1
Summary: Takes pictures of code!
Home-page: https://github.com/none-None1/sourceshot
Keywords: code,picture
Requires-Python: >=3.6
Requires-Dist: pygments (>=0.7)
Requires-Dist: pillow (<10)
Requires-Dist: numpy
Requires-Dist: opencv-python
Requires-Dist: colorama
